CS2APY/CS2APY.py
CS2APY/__init__.py
CS2APY/scoreboard_pb2.py
CS2APY-0.5.dist-info/LICENSE
CS2APY-0.5.dist-info/METADATA
CS2APY-0.5.dist-info/WHEEL
CS2APY-0.5.dist-info/top_level.txt
CS2APY-0.5.dist-info/RECORD
