Metadata-Version: 2.1
Name: CS2APY
Version: 0.5
Summary: A high-level Python3 wrapper module for the Counter-Strike: 2 Premier Leaderboards API.
Home-page: https://github.com/j4mesli/cs2leaderboard-APY
Author: James Li
Author-email: jamesli196q@gmail.com
Classifier: Programming Language :: Python :: 3
Classifier: License :: OSI Approved :: MIT License
Classifier: Operating System :: OS Independent
Requires-Python: >=3.6
License-File: LICENSE
